stackingNT/__init__.py
stackingNT/stackingnonlineartransformations.py
stackingNT-0.0.2.dist-info/METADATA
stackingNT-0.0.2.dist-info/WHEEL
stackingNT-0.0.2.dist-info/top_level.txt
stackingNT-0.0.2.dist-info/RECORD
