Metadata-Version: 2.1
Name: stackingNT
Version: 0.0.2
Summary: Stacking algorithm optimisation
Home-page: UNKNOWN
Author: caoxinyu
Author-email: 398424191@qq.com
License: UNKNOWN
Keywords: python,menu,dumb_menu,windows,mac,linux
Platform: UNKNOWN
Classifier: Development Status :: 1 - Planning
Classifier: Intended Audience :: Developers
Classifier: Programming Language :: Python :: 3
Classifier: Operating System :: Unix
Classifier: Operating System :: MacOS :: MacOS X
Classifier: Operating System :: Microsoft :: Windows
